{"materials":[{"id":-112534,"path":"Default UI Material","assetBundleId":-1,"data":["Default UI Material",0,64,3000,0,[["_StencilComp",8],["_Stencil",0],["_StencilOp",0],["_StencilWriteMask",255],["_StencilReadMask",255],["_ColorMask",15],["_UseUIAlphaClip",0]],[["_Color",1,1,1,1]],[["_MainTex_ST",1,1,0,0]],[["_MainTex",null,null]],[]]}],"scenes":[{"id":0,"name":"SampleScene","path":"Assets/Content/Scenes/SampleScene.unity","assetBundleId":-1,"data":["SampleScene",0,1],"objects":[{"id":52642,"path":"Main Camera","assetBundleId":0,"components":[{"type":1,"id":52646,"data":[1.22043013572693,0,5,0,0,0,1,0.300000011920929,1000,60,-1,1,-1,[0,0,1,1],null,null,0,50,36,24,0,0,2,0,1,1]},{"type":2,"id":52644,"data":[]},{"type":3,"id":52650,"enabled":1,"class":4,"data":[1,2,2,0,[],-1,1,null,null,2,1,0,2,0,0,1,1,1,0,0,0,0,0,0,0,0,0,0,0,2,[3,0.100000001490116,1,0,0.899999976158142,0]]}],"children":[],"data":["Main Camera",4,1,0,0]},{"id":52652,"path":"Directional Light","assetBundleId":0,"components":[{"type":5,"id":52654,"data":[1,1,1,1,1,-1,2,10,30,2,0.400000005960464,0.0500000007450581,1,-1,4,0,null,null,10,0.200000002980232,-1,1]},{"type":3,"id":52658,"enabled":1,"class":6,"data":[3,1,2,1,1,0,1,1,1,1,0,0,1]}],"children":[],"data":["Directional Light",0,1,0,0]}],"render_settings":{"data":[1,1,0,0.211999997496605,0.226999998092651,0.25900000333786,1,0.211999997496605,0.226999998092651,0.25900000333786,1,0.0469999983906746,0.0430000014603138,0.0350000001490116,1,0.114000000059605,0.125,0.133000001311302,1,0.5,0.5,0.5,1,300,0,0.00999999977648258,0,7,588,3,[],[[0,0],[0,0],[0,0],[0,0],[0,0],[0,0]],1,2,1,[0.1802835,-0.005682554,-0.01256066,0.007252007,0.005699947,-0.009872363,0.01033013,-0.01043636,0.02503555,0.2257138,0.04134344,-0.01975334,0.01140323,0.009111935,-0.01578324,0.01437993,-0.01522379,0.03443607,0.3069224,0.1274844,-0.03405331,0.01965661,0.01636517,-0.02834914,0.01771558,-0.02208527,0.04046547],[0,0,0,0,0,0,0,0,0,0,0,0,0,0,0,0,0,0,0,0,0,0,0,0,0,0,0],0,null,null,8,-102680,0,128,52654,2,1,0,1]},"transform_ids":[52648,52656],"local_positions":[0,1,-10,0,3,0],"local_rotations":[0,0,0,1,0.408217877149582,-0.234569683670998,0.109381631016731,0.875426113605499],"local_scales":[1,1,1,1,1,1],"shaders":[280,106,386,64],"transforms":{"marker":[0,80],"count":2,"offsets":{"positions":0,"rotations":6,"scales":14}},"transformsIds":{"marker":[80,8],"offsets":{"indices":0}}}],"shaders":[{"id":106,"assetBundleId":-1,"data":[[],"Hidden/InternalErrorShader",null,[],[[0,0,"",0,"",0,[4,null],[1,null],[2,null],[[1,null],[0,null],[0,null]],[[1,null],[0,null],[0,null]],[15,null],[0,null],[0,null],[0,null],[255,null],[255,null],[[0,null],[0,null],[0,null],[8,null]],[[0,null],[0,null],[0,null],[8,null]],[[0,null],[0,null],[0,null],[8,null]],[],[],[],[[0,0,[],0,1,0,0]],[],0],[1,0,"DepthNormalsOnly",0,"",0,[4,null],[1,null],[2,null],[[1,null],[0,null],[0,null]],[[1,null],[0,null],[0,null]],[0,null],[0,null],[0,null],[0,null],[255,null],[255,null],[[0,null],[0,null],[0,null],[8,null]],[[0,null],[0,null],[0,null],[8,null]],[[0,null],[0,null],[0,null],[8,null]],[["LIGHTMODE","DepthNormalsOnly"]],[],[],[[1,0,[],2,1,0,0]],[],0],[2,0,"DepthOnly",13,"",0,[4,null],[1,null],[2,null],[[1,null],[0,null],[0,null]],[[1,null],[0,null],[0,null]],[0,null],[0,null],[0,null],[0,null],[255,null],[255,null],[[0,null],[0,null],[0,null],[8,null]],[[0,null],[0,null],[0,null],[8,null]],[[0,null],[0,null],[0,null],[8,null]],[["LIGHTMODE","DepthOnly"]],[],[],[[2,0,[],2,1,0,0]],[],0]],[],[],null,null,0,1,0,0,0]}],"textures":[{"id":-216654,"type":0,"path":"Assets/Content/Scenes/SampleScene.unity/PrefilteredEnvironment.exr","assetBundleId":-1,"data":["",512,256,1,1,1,1,4,0,0,1,4,1,1,0,0]}],"urp-assets":[{"id":24,"assetBundleId":-1,"data":[0,[0,2,1],1,0,1024,0,2,50,1,0.25,0.100000001490116,0.300000011920929,0.0670000016689301,0.200000002980232,0.467000007629395,0.100000001490116,1,1,0,0,[-1,-1,[],"URP-Performant-Renderer"]]}]}